new_reader.py
new_reader-0.1.13.dist-info/METADATA
new_reader-0.1.13.dist-info/WHEEL
new_reader-0.1.13.dist-info/top_level.txt
new_reader-0.1.13.dist-info/RECORD
