Metadata-Version: 2.1
Name: new-reader
Version: 0.1.13
Summary: Read http(s), multicast, and udp streams like files
Home-page: https://github.com/futzu/new_reader
Author: Adrian
Author-email: spam@iodisco.com
License: UNKNOWN
Platform: all
Classifier: License :: OSI Approved :: MIT License
Classifier: Operating System :: OS Independent
Classifier: Programming Language :: Python :: 3.6
Classifier: Programming Language :: Python :: Implementation :: PyPy
Classifier: Programming Language :: Python :: Implementation :: CPython
Requires-Python: >=3.6
